{
  "type": "File",
  "start": 0,
  "end": 265,
  "loc": {
    "start": {
      "line": 1,
      "column": 0
    },
    "end": {
      "line": 14,
      "column": 0
    }
  },
  "program": {
    "type": "Program",
    "start": 0,
    "end": 265,
    "loc": {
      "start": {
        "line": 1,
        "column": 0
      },
      "end": {
        "line": 14,
        "column": 0
      }
    },
    "sourceType": "module",
    "body": [
      {
        "type": "ExpressionStatement",
        "start": 0,
        "end": 134,
        "loc": {
          "start": {
            "line": 1,
            "column": 0
          },
          "end": {
            "line": 4,
            "column": 2
          }
        },
        "expression": {
          "type": "AssignmentExpression",
          "start": 0,
          "end": 133,
          "loc": {
            "start": {
              "line": 1,
              "column": 0
            },
            "end": {
              "line": 4,
              "column": 1
            }
          },
          "operator": "=",
          "left": {
            "type": "MemberExpression",
            "start": 0,
            "end": 22,
            "loc": {
              "start": {
                "line": 1,
                "column": 0
              },
              "end": {
                "line": 1,
                "column": 22
              }
            },
            "object": {
              "type": "Identifier",
              "start": 0,
              "end": 7,
              "loc": {
                "start": {
                  "line": 1,
                  "column": 0
                },
                "end": {
                  "line": 1,
                  "column": 7
                },
                "identifierName": "exports"
              },
              "name": "exports"
            },
            "property": {
              "type": "Identifier",
              "start": 8,
              "end": 22,
              "loc": {
                "start": {
                  "line": 1,
                  "column": 8
                },
                "end": {
                  "line": 1,
                  "column": 22
                },
                "identifierName": "formItemLayout"
              },
              "name": "formItemLayout"
            },
            "computed": false
          },
          "right": {
            "type": "ObjectExpression",
            "start": 25,
            "end": 133,
            "loc": {
              "start": {
                "line": 1,
                "column": 25
              },
              "end": {
                "line": 4,
                "column": 1
              }
            },
            "properties": [
              {
                "type": "ObjectProperty",
                "start": 29,
                "end": 76,
                "loc": {
                  "start": {
                    "line": 2,
                    "column": 2
                  },
                  "end": {
                    "line": 2,
                    "column": 49
                  }
                },
                "method": false,
                "shorthand": false,
                "computed": false,
                "key": {
                  "type": "Identifier",
                  "start": 29,
                  "end": 37,
                  "loc": {
                    "start": {
                      "line": 2,
                      "column": 2
                    },
                    "end": {
                      "line": 2,
                      "column": 10
                    },
                    "identifierName": "labelCol"
                  },
                  "name": "labelCol"
                },
                "value": {
                  "type": "ObjectExpression",
                  "start": 39,
                  "end": 76,
                  "loc": {
                    "start": {
                      "line": 2,
                      "column": 12
                    },
                    "end": {
                      "line": 2,
                      "column": 49
                    }
                  },
                  "properties": [
                    {
                      "type": "ObjectProperty",
                      "start": 41,
                      "end": 57,
                      "loc": {
                        "start": {
                          "line": 2,
                          "column": 14
                        },
                        "end": {
                          "line": 2,
                          "column": 30
                        }
                      },
                      "method": false,
                      "shorthand": false,
                      "computed": false,
                      "key": {
                        "type": "Identifier",
                        "start": 41,
                        "end": 43,
                        "loc": {
                          "start": {
                            "line": 2,
                            "column": 14
                          },
                          "end": {
                            "line": 2,
                            "column": 16
                          },
                          "identifierName": "xs"
                        },
                        "name": "xs"
                      },
                      "value": {
                        "type": "ObjectExpression",
                        "start": 45,
                        "end": 57,
                        "loc": {
                          "start": {
                            "line": 2,
                            "column": 18
                          },
                          "end": {
                            "line": 2,
                            "column": 30
                          }
                        },
                        "properties": [
                          {
                            "type": "ObjectProperty",
                            "start": 47,
                            "end": 55,
                            "loc": {
                              "start": {
                                "line": 2,
                                "column": 20
                              },
                              "end": {
                                "line": 2,
                                "column": 28
                              }
                            },
                            "method": false,
                            "shorthand": false,
                            "computed": false,
                            "key": {
                              "type": "Identifier",
                              "start": 47,
                              "end": 51,
                              "loc": {
                                "start": {
                                  "line": 2,
                                  "column": 20
                                },
                                "end": {
                                  "line": 2,
                                  "column": 24
                                },
                                "identifierName": "span"
                              },
                              "name": "span"
                            },
                            "value": {
                              "type": "NumericLiteral",
                              "start": 53,
                              "end": 55,
                              "loc": {
                                "start": {
                                  "line": 2,
                                  "column": 26
                                },
                                "end": {
                                  "line": 2,
                                  "column": 28
                                }
                              },
                              "extra": {
                                "rawValue": 24,
                                "raw": "24"
                              },
                              "value": 24
                            }
                          }
                        ]
                      }
                    },
                    {
                      "type": "ObjectProperty",
                      "start": 59,
                      "end": 74,
                      "loc": {
                        "start": {
                          "line": 2,
                          "column": 32
                        },
                        "end": {
                          "line": 2,
                          "column": 47
                        }
                      },
                      "method": false,
                      "shorthand": false,
                      "computed": false,
                      "key": {
                        "type": "Identifier",
                        "start": 59,
                        "end": 61,
                        "loc": {
                          "start": {
                            "line": 2,
                            "column": 32
                          },
                          "end": {
                            "line": 2,
                            "column": 34
                          },
                          "identifierName": "sm"
                        },
                        "name": "sm"
                      },
                      "value": {
                        "type": "ObjectExpression",
                        "start": 63,
                        "end": 74,
                        "loc": {
                          "start": {
                            "line": 2,
                            "column": 36
                          },
                          "end": {
                            "line": 2,
                            "column": 47
                          }
                        },
                        "properties": [
                          {
                            "type": "ObjectProperty",
                            "start": 65,
                            "end": 72,
                            "loc": {
                              "start": {
                                "line": 2,
                                "column": 38
                              },
                              "end": {
                                "line": 2,
                                "column": 45
                              }
                            },
                            "method": false,
                            "shorthand": false,
                            "computed": false,
                            "key": {
                              "type": "Identifier",
                              "start": 65,
                              "end": 69,
                              "loc": {
                                "start": {
                                  "line": 2,
                                  "column": 38
                                },
                                "end": {
                                  "line": 2,
                                  "column": 42
                                },
                                "identifierName": "span"
                              },
                              "name": "span"
                            },
                            "value": {
                              "type": "NumericLiteral",
                              "start": 71,
                              "end": 72,
                              "loc": {
                                "start": {
                                  "line": 2,
                                  "column": 44
                                },
                                "end": {
                                  "line": 2,
                                  "column": 45
                                }
                              },
                              "extra": {
                                "rawValue": 6,
                                "raw": "6"
                              },
                              "value": 6
                            }
                          }
                        ]
                      }
                    }
                  ]
                }
              },
              {
                "type": "ObjectProperty",
                "start": 80,
                "end": 130,
                "loc": {
                  "start": {
                    "line": 3,
                    "column": 2
                  },
                  "end": {
                    "line": 3,
                    "column": 52
                  }
                },
                "method": false,
                "shorthand": false,
                "computed": false,
                "key": {
                  "type": "Identifier",
                  "start": 80,
                  "end": 90,
                  "loc": {
                    "start": {
                      "line": 3,
                      "column": 2
                    },
                    "end": {
                      "line": 3,
                      "column": 12
                    },
                    "identifierName": "wrapperCol"
                  },
                  "name": "wrapperCol"
                },
                "value": {
                  "type": "ObjectExpression",
                  "start": 92,
                  "end": 130,
                  "loc": {
                    "start": {
                      "line": 3,
                      "column": 14
                    },
                    "end": {
                      "line": 3,
                      "column": 52
                    }
                  },
                  "properties": [
                    {
                      "type": "ObjectProperty",
                      "start": 94,
                      "end": 110,
                      "loc": {
                        "start": {
                          "line": 3,
                          "column": 16
                        },
                        "end": {
                          "line": 3,
                          "column": 32
                        }
                      },
                      "method": false,
                      "shorthand": false,
                      "computed": false,
                      "key": {
                        "type": "Identifier",
                        "start": 94,
                        "end": 96,
                        "loc": {
                          "start": {
                            "line": 3,
                            "column": 16
                          },
                          "end": {
                            "line": 3,
                            "column": 18
                          },
                          "identifierName": "xs"
                        },
                        "name": "xs"
                      },
                      "value": {
                        "type": "ObjectExpression",
                        "start": 98,
                        "end": 110,
                        "loc": {
                          "start": {
                            "line": 3,
                            "column": 20
                          },
                          "end": {
                            "line": 3,
                            "column": 32
                          }
                        },
                        "properties": [
                          {
                            "type": "ObjectProperty",
                            "start": 100,
                            "end": 108,
                            "loc": {
                              "start": {
                                "line": 3,
                                "column": 22
                              },
                              "end": {
                                "line": 3,
                                "column": 30
                              }
                            },
                            "method": false,
                            "shorthand": false,
                            "computed": false,
                            "key": {
                              "type": "Identifier",
                              "start": 100,
                              "end": 104,
                              "loc": {
                                "start": {
                                  "line": 3,
                                  "column": 22
                                },
                                "end": {
                                  "line": 3,
                                  "column": 26
                                },
                                "identifierName": "span"
                              },
                              "name": "span"
                            },
                            "value": {
                              "type": "NumericLiteral",
                              "start": 106,
                              "end": 108,
                              "loc": {
                                "start": {
                                  "line": 3,
                                  "column": 28
                                },
                                "end": {
                                  "line": 3,
                                  "column": 30
                                }
                              },
                              "extra": {
                                "rawValue": 24,
                                "raw": "24"
                              },
                              "value": 24
                            }
                          }
                        ]
                      }
                    },
                    {
                      "type": "ObjectProperty",
                      "start": 112,
                      "end": 128,
                      "loc": {
                        "start": {
                          "line": 3,
                          "column": 34
                        },
                        "end": {
                          "line": 3,
                          "column": 50
                        }
                      },
                      "method": false,
                      "shorthand": false,
                      "computed": false,
                      "key": {
                        "type": "Identifier",
                        "start": 112,
                        "end": 114,
                        "loc": {
                          "start": {
                            "line": 3,
                            "column": 34
                          },
                          "end": {
                            "line": 3,
                            "column": 36
                          },
                          "identifierName": "sm"
                        },
                        "name": "sm"
                      },
                      "value": {
                        "type": "ObjectExpression",
                        "start": 116,
                        "end": 128,
                        "loc": {
                          "start": {
                            "line": 3,
                            "column": 38
                          },
                          "end": {
                            "line": 3,
                            "column": 50
                          }
                        },
                        "properties": [
                          {
                            "type": "ObjectProperty",
                            "start": 118,
                            "end": 126,
                            "loc": {
                              "start": {
                                "line": 3,
                                "column": 40
                              },
                              "end": {
                                "line": 3,
                                "column": 48
                              }
                            },
                            "method": false,
                            "shorthand": false,
                            "computed": false,
                            "key": {
                              "type": "Identifier",
                              "start": 118,
                              "end": 122,
                              "loc": {
                                "start": {
                                  "line": 3,
                                  "column": 40
                                },
                                "end": {
                                  "line": 3,
                                  "column": 44
                                },
                                "identifierName": "span"
                              },
                              "name": "span"
                            },
                            "value": {
                              "type": "NumericLiteral",
                              "start": 124,
                              "end": 126,
                              "loc": {
                                "start": {
                                  "line": 3,
                                  "column": 46
                                },
                                "end": {
                                  "line": 3,
                                  "column": 48
                                }
                              },
                              "extra": {
                                "rawValue": 12,
                                "raw": "12"
                              },
                              "value": 12
                            }
                          }
                        ]
                      }
                    }
                  ]
                }
              }
            ]
          }
        }
      },
      {
        "type": "ExpressionStatement",
        "start": 136,
        "end": 200,
        "loc": {
          "start": {
            "line": 6,
            "column": 0
          },
          "end": {
            "line": 8,
            "column": 2
          }
        },
        "expression": {
          "type": "AssignmentExpression",
          "start": 136,
          "end": 199,
          "loc": {
            "start": {
              "line": 6,
              "column": 0
            },
            "end": {
              "line": 8,
              "column": 1
            }
          },
          "operator": "=",
          "left": {
            "type": "MemberExpression",
            "start": 136,
            "end": 154,
            "loc": {
              "start": {
                "line": 6,
                "column": 0
              },
              "end": {
                "line": 6,
                "column": 18
              }
            },
            "object": {
              "type": "Identifier",
              "start": 136,
              "end": 143,
              "loc": {
                "start": {
                  "line": 6,
                  "column": 0
                },
                "end": {
                  "line": 6,
                  "column": 7
                },
                "identifierName": "exports"
              },
              "name": "exports"
            },
            "property": {
              "type": "Identifier",
              "start": 144,
              "end": 154,
              "loc": {
                "start": {
                  "line": 6,
                  "column": 8
                },
                "end": {
                  "line": 6,
                  "column": 18
                },
                "identifierName": "tailLayout"
              },
              "name": "tailLayout"
            },
            "computed": false
          },
          "right": {
            "type": "ObjectExpression",
            "start": 157,
            "end": 199,
            "loc": {
              "start": {
                "line": 6,
                "column": 21
              },
              "end": {
                "line": 8,
                "column": 1
              }
            },
            "properties": [
              {
                "type": "ObjectProperty",
                "start": 161,
                "end": 196,
                "loc": {
                  "start": {
                    "line": 7,
                    "column": 2
                  },
                  "end": {
                    "line": 7,
                    "column": 37
                  }
                },
                "method": false,
                "shorthand": false,
                "computed": false,
                "key": {
                  "type": "Identifier",
                  "start": 161,
                  "end": 171,
                  "loc": {
                    "start": {
                      "line": 7,
                      "column": 2
                    },
                    "end": {
                      "line": 7,
                      "column": 12
                    },
                    "identifierName": "wrapperCol"
                  },
                  "name": "wrapperCol"
                },
                "value": {
                  "type": "ObjectExpression",
                  "start": 173,
                  "end": 196,
                  "loc": {
                    "start": {
                      "line": 7,
                      "column": 14
                    },
                    "end": {
                      "line": 7,
                      "column": 37
                    }
                  },
                  "properties": [
                    {
                      "type": "ObjectProperty",
                      "start": 175,
                      "end": 184,
                      "loc": {
                        "start": {
                          "line": 7,
                          "column": 16
                        },
                        "end": {
                          "line": 7,
                          "column": 25
                        }
                      },
                      "method": false,
                      "shorthand": false,
                      "computed": false,
                      "key": {
                        "type": "Identifier",
                        "start": 175,
                        "end": 181,
                        "loc": {
                          "start": {
                            "line": 7,
                            "column": 16
                          },
                          "end": {
                            "line": 7,
                            "column": 22
                          },
                          "identifierName": "offset"
                        },
                        "name": "offset"
                      },
                      "value": {
                        "type": "NumericLiteral",
                        "start": 183,
                        "end": 184,
                        "loc": {
                          "start": {
                            "line": 7,
                            "column": 24
                          },
                          "end": {
                            "line": 7,
                            "column": 25
                          }
                        },
                        "extra": {
                          "rawValue": 8,
                          "raw": "8"
                        },
                        "value": 8
                      }
                    },
                    {
                      "type": "ObjectProperty",
                      "start": 186,
                      "end": 194,
                      "loc": {
                        "start": {
                          "line": 7,
                          "column": 27
                        },
                        "end": {
                          "line": 7,
                          "column": 35
                        }
                      },
                      "method": false,
                      "shorthand": false,
                      "computed": false,
                      "key": {
                        "type": "Identifier",
                        "start": 186,
                        "end": 190,
                        "loc": {
                          "start": {
                            "line": 7,
                            "column": 27
                          },
                          "end": {
                            "line": 7,
                            "column": 31
                          },
                          "identifierName": "span"
                        },
                        "name": "span"
                      },
                      "value": {
                        "type": "NumericLiteral",
                        "start": 192,
                        "end": 194,
                        "loc": {
                          "start": {
                            "line": 7,
                            "column": 33
                          },
                          "end": {
                            "line": 7,
                            "column": 35
                          }
                        },
                        "extra": {
                          "rawValue": 16,
                          "raw": "16"
                        },
                        "value": 16
                      }
                    }
                  ]
                }
              }
            ]
          }
        }
      },
      {
        "type": "ExpressionStatement",
        "start": 202,
        "end": 264,
        "loc": {
          "start": {
            "line": 10,
            "column": 0
          },
          "end": {
            "line": 13,
            "column": 2
          }
        },
        "expression": {
          "type": "AssignmentExpression",
          "start": 202,
          "end": 263,
          "loc": {
            "start": {
              "line": 10,
              "column": 0
            },
            "end": {
              "line": 13,
              "column": 1
            }
          },
          "operator": "=",
          "left": {
            "type": "MemberExpression",
            "start": 202,
            "end": 220,
            "loc": {
              "start": {
                "line": 10,
                "column": 0
              },
              "end": {
                "line": 10,
                "column": 18
              }
            },
            "object": {
              "type": "Identifier",
              "start": 202,
              "end": 209,
              "loc": {
                "start": {
                  "line": 10,
                  "column": 0
                },
                "end": {
                  "line": 10,
                  "column": 7
                },
                "identifierName": "exports"
              },
              "name": "exports"
            },
            "property": {
              "type": "Identifier",
              "start": 210,
              "end": 220,
              "loc": {
                "start": {
                  "line": 10,
                  "column": 8
                },
                "end": {
                  "line": 10,
                  "column": 18
                },
                "identifierName": "cardLayout"
              },
              "name": "cardLayout"
            },
            "computed": false
          },
          "right": {
            "type": "ObjectExpression",
            "start": 223,
            "end": 263,
            "loc": {
              "start": {
                "line": 10,
                "column": 21
              },
              "end": {
                "line": 13,
                "column": 1
              }
            },
            "properties": [
              {
                "type": "ObjectProperty",
                "start": 227,
                "end": 243,
                "loc": {
                  "start": {
                    "line": 11,
                    "column": 2
                  },
                  "end": {
                    "line": 11,
                    "column": 18
                  }
                },
                "method": false,
                "shorthand": false,
                "computed": false,
                "key": {
                  "type": "Identifier",
                  "start": 227,
                  "end": 239,
                  "loc": {
                    "start": {
                      "line": 11,
                      "column": 2
                    },
                    "end": {
                      "line": 11,
                      "column": 14
                    },
                    "identifierName": "borderRadius"
                  },
                  "name": "borderRadius"
                },
                "value": {
                  "type": "NumericLiteral",
                  "start": 241,
                  "end": 243,
                  "loc": {
                    "start": {
                      "line": 11,
                      "column": 16
                    },
                    "end": {
                      "line": 11,
                      "column": 18
                    }
                  },
                  "extra": {
                    "rawValue": 10,
                    "raw": "10"
                  },
                  "value": 10
                }
              },
              {
                "type": "ObjectProperty",
                "start": 247,
                "end": 260,
                "loc": {
                  "start": {
                    "line": 12,
                    "column": 2
                  },
                  "end": {
                    "line": 12,
                    "column": 15
                  }
                },
                "method": false,
                "shorthand": false,
                "computed": false,
                "key": {
                  "type": "Identifier",
                  "start": 247,
                  "end": 256,
                  "loc": {
                    "start": {
                      "line": 12,
                      "column": 2
                    },
                    "end": {
                      "line": 12,
                      "column": 11
                    },
                    "identifierName": "marginTop"
                  },
                  "name": "marginTop"
                },
                "value": {
                  "type": "NumericLiteral",
                  "start": 258,
                  "end": 260,
                  "loc": {
                    "start": {
                      "line": 12,
                      "column": 13
                    },
                    "end": {
                      "line": 12,
                      "column": 15
                    }
                  },
                  "extra": {
                    "rawValue": 10,
                    "raw": "10"
                  },
                  "value": 10
                }
              }
            ]
          }
        }
      }
    ],
    "directives": []
  },
  "comments": [],
  "tokens": [
    {
      "type": {
        "label": "name",
        "beforeExpr": false,
        "startsExpr": true,
        "rightAssociative": false,
        "isLoop": false,
        "isAssign": false,
        "prefix": false,
        "postfix": false,
        "binop": null
      },
      "value": "exports",
      "start": 0,
      "end": 7,
      "loc": {
        "start": {
          "line": 1,
          "column": 0
        },
        "end": {
          "line": 1,
          "column": 7
        }
      }
    },
    {
      "type": {
        "label": ".",
        "beforeExpr": false,
        "startsExpr": false,
        "rightAssociative": false,
        "isLoop": false,
        "isAssign": false,
        "prefix": false,
        "postfix": false,
        "binop": null,
        "updateContext": null
      },
      "start": 7,
      "end": 8,
      "loc": {
        "start": {
          "line": 1,
          "column": 7
        },
        "end": {
          "line": 1,
          "column": 8
        }
      }
    },
    {
      "type": {
        "label": "name",
        "beforeExpr": false,
        "startsExpr": true,
        "rightAssociative": false,
        "isLoop": false,
        "isAssign": false,
        "prefix": false,
        "postfix": false,
        "binop": null
      },
      "value": "formItemLayout",
      "start": 8,
      "end": 22,
      "loc": {
        "start": {
          "line": 1,
          "column": 8
        },
        "end": {
          "line": 1,
          "column": 22
        }
      }
    },
    {
      "type": {
        "label": "=",
        "beforeExpr": true,
        "startsExpr": false,
        "rightAssociative": false,
        "isLoop": false,
        "isAssign": true,
        "prefix": false,
        "postfix": false,
        "binop": null,
        "updateContext": null
      },
      "value": "=",
      "start": 23,
      "end": 24,
      "loc": {
        "start": {
          "line": 1,
          "column": 23
        },
        "end": {
          "line": 1,
          "column": 24
        }
      }
    },
    {
      "type": {
        "label": "{",
        "beforeExpr": true,
        "startsExpr": true,
        "rightAssociative": false,
        "isLoop": false,
        "isAssign": false,
        "prefix": false,
        "postfix": false,
        "binop": null
      },
      "start": 25,
      "end": 26,
      "loc": {
        "start": {
          "line": 1,
          "column": 25
        },
        "end": {
          "line": 1,
          "column": 26
        }
      }
    },
    {
      "type": {
        "label": "name",
        "beforeExpr": false,
        "startsExpr": true,
        "rightAssociative": false,
        "isLoop": false,
        "isAssign": false,
        "prefix": false,
        "postfix": false,
        "binop": null
      },
      "value": "labelCol",
      "start": 29,
      "end": 37,
      "loc": {
        "start": {
          "line": 2,
          "column": 2
        },
        "end": {
          "line": 2,
          "column": 10
        }
      }
    },
    {
      "type": {
        "label": ":",
        "beforeExpr": true,
        "startsExpr": false,
        "rightAssociative": false,
        "isLoop": false,
        "isAssign": false,
        "prefix": false,
        "postfix": false,
        "binop": null,
        "updateContext": null
      },
      "start": 37,
      "end": 38,
      "loc": {
        "start": {
          "line": 2,
          "column": 10
        },
        "end": {
          "line": 2,
          "column": 11
        }
      }
    },
    {
      "type": {
        "label": "{",
        "beforeExpr": true,
        "startsExpr": true,
        "rightAssociative": false,
        "isLoop": false,
        "isAssign": false,
        "prefix": false,
        "postfix": false,
        "binop": null
      },
      "start": 39,
      "end": 40,
      "loc": {
        "start": {
          "line": 2,
          "column": 12
        },
        "end": {
          "line": 2,
          "column": 13
        }
      }
    },
    {
      "type": {
        "label": "name",
        "beforeExpr": false,
        "startsExpr": true,
        "rightAssociative": false,
        "isLoop": false,
        "isAssign": false,
        "prefix": false,
        "postfix": false,
        "binop": null
      },
      "value": "xs",
      "start": 41,
      "end": 43,
      "loc": {
        "start": {
          "line": 2,
          "column": 14
        },
        "end": {
          "line": 2,
          "column": 16
        }
      }
    },
    {
      "type": {
        "label": ":",
        "beforeExpr": true,
        "startsExpr": false,
        "rightAssociative": false,
        "isLoop": false,
        "isAssign": false,
        "prefix": false,
        "postfix": false,
        "binop": null,
        "updateContext": null
      },
      "start": 43,
      "end": 44,
      "loc": {
        "start": {
          "line": 2,
          "column": 16
        },
        "end": {
          "line": 2,
          "column": 17
        }
      }
    },
    {
      "type": {
        "label": "{",
        "beforeExpr": true,
        "startsExpr": true,
        "rightAssociative": false,
        "isLoop": false,
        "isAssign": false,
        "prefix": false,
        "postfix": false,
        "binop": null
      },
      "start": 45,
      "end": 46,
      "loc": {
        "start": {
          "line": 2,
          "column": 18
        },
        "end": {
          "line": 2,
          "column": 19
        }
      }
    },
    {
      "type": {
        "label": "name",
        "beforeExpr": false,
        "startsExpr": true,
        "rightAssociative": false,
        "isLoop": false,
        "isAssign": false,
        "prefix": false,
        "postfix": false,
        "binop": null
      },
      "value": "span",
      "start": 47,
      "end": 51,
      "loc": {
        "start": {
          "line": 2,
          "column": 20
        },
        "end": {
          "line": 2,
          "column": 24
        }
      }
    },
    {
      "type": {
        "label": ":",
        "beforeExpr": true,
        "startsExpr": false,
        "rightAssociative": false,
        "isLoop": false,
        "isAssign": false,
        "prefix": false,
        "postfix": false,
        "binop": null,
        "updateContext": null
      },
      "start": 51,
      "end": 52,
      "loc": {
        "start": {
          "line": 2,
          "column": 24
        },
        "end": {
          "line": 2,
          "column": 25
        }
      }
    },
    {
      "type": {
        "label": "num",
        "beforeExpr": false,
        "startsExpr": true,
        "rightAssociative": false,
        "isLoop": false,
        "isAssign": false,
        "prefix": false,
        "postfix": false,
        "binop": null,
        "updateContext": null
      },
      "value": 24,
      "start": 53,
      "end": 55,
      "loc": {
        "start": {
          "line": 2,
          "column": 26
        },
        "end": {
          "line": 2,
          "column": 28
        }
      }
    },
    {
      "type": {
        "label": "}",
        "beforeExpr": false,
        "startsExpr": false,
        "rightAssociative": false,
        "isLoop": false,
        "isAssign": false,
        "prefix": false,
        "postfix": false,
        "binop": null
      },
      "start": 56,
      "end": 57,
      "loc": {
        "start": {
          "line": 2,
          "column": 29
        },
        "end": {
          "line": 2,
          "column": 30
        }
      }
    },
    {
      "type": {
        "label": ",",
        "beforeExpr": true,
        "startsExpr": false,
        "rightAssociative": false,
        "isLoop": false,
        "isAssign": false,
        "prefix": false,
        "postfix": false,
        "binop": null,
        "updateContext": null
      },
      "start": 57,
      "end": 58,
      "loc": {
        "start": {
          "line": 2,
          "column": 30
        },
        "end": {
          "line": 2,
          "column": 31
        }
      }
    },
    {
      "type": {
        "label": "name",
        "beforeExpr": false,
        "startsExpr": true,
        "rightAssociative": false,
        "isLoop": false,
        "isAssign": false,
        "prefix": false,
        "postfix": false,
        "binop": null
      },
      "value": "sm",
      "start": 59,
      "end": 61,
      "loc": {
        "start": {
          "line": 2,
          "column": 32
        },
        "end": {
          "line": 2,
          "column": 34
        }
      }
    },
    {
      "type": {
        "label": ":",
        "beforeExpr": true,
        "startsExpr": false,
        "rightAssociative": false,
        "isLoop": false,
        "isAssign": false,
        "prefix": false,
        "postfix": false,
        "binop": null,
        "updateContext": null
      },
      "start": 61,
      "end": 62,
      "loc": {
        "start": {
          "line": 2,
          "column": 34
        },
        "end": {
          "line": 2,
          "column": 35
        }
      }
    },
    {
      "type": {
        "label": "{",
        "beforeExpr": true,
        "startsExpr": true,
        "rightAssociative": false,
        "isLoop": false,
        "isAssign": false,
        "prefix": false,
        "postfix": false,
        "binop": null
      },
      "start": 63,
      "end": 64,
      "loc": {
        "start": {
          "line": 2,
          "column": 36
        },
        "end": {
          "line": 2,
          "column": 37
        }
      }
    },
    {
      "type": {
        "label": "name",
        "beforeExpr": false,
        "startsExpr": true,
        "rightAssociative": false,
        "isLoop": false,
        "isAssign": false,
        "prefix": false,
        "postfix": false,
        "binop": null
      },
      "value": "span",
      "start": 65,
      "end": 69,
      "loc": {
        "start": {
          "line": 2,
          "column": 38
        },
        "end": {
          "line": 2,
          "column": 42
        }
      }
    },
    {
      "type": {
        "label": ":",
        "beforeExpr": true,
        "startsExpr": false,
        "rightAssociative": false,
        "isLoop": false,
        "isAssign": false,
        "prefix": false,
        "postfix": false,
        "binop": null,
        "updateContext": null
      },
      "start": 69,
      "end": 70,
      "loc": {
        "start": {
          "line": 2,
          "column": 42
        },
        "end": {
          "line": 2,
          "column": 43
        }
      }
    },
    {
      "type": {
        "label": "num",
        "beforeExpr": false,
        "startsExpr": true,
        "rightAssociative": false,
        "isLoop": false,
        "isAssign": false,
        "prefix": false,
        "postfix": false,
        "binop": null,
        "updateContext": null
      },
      "value": 6,
      "start": 71,
      "end": 72,
      "loc": {
        "start": {
          "line": 2,
          "column": 44
        },
        "end": {
          "line": 2,
          "column": 45
        }
      }
    },
    {
      "type": {
        "label": "}",
        "beforeExpr": false,
        "startsExpr": false,
        "rightAssociative": false,
        "isLoop": false,
        "isAssign": false,
        "prefix": false,
        "postfix": false,
        "binop": null
      },
      "start": 73,
      "end": 74,
      "loc": {
        "start": {
          "line": 2,
          "column": 46
        },
        "end": {
          "line": 2,
          "column": 47
        }
      }
    },
    {
      "type": {
        "label": "}",
        "beforeExpr": false,
        "startsExpr": false,
        "rightAssociative": false,
        "isLoop": false,
        "isAssign": false,
        "prefix": false,
        "postfix": false,
        "binop": null
      },
      "start": 75,
      "end": 76,
      "loc": {
        "start": {
          "line": 2,
          "column": 48
        },
        "end": {
          "line": 2,
          "column": 49
        }
      }
    },
    {
      "type": {
        "label": ",",
        "beforeExpr": true,
        "startsExpr": false,
        "rightAssociative": false,
        "isLoop": false,
        "isAssign": false,
        "prefix": false,
        "postfix": false,
        "binop": null,
        "updateContext": null
      },
      "start": 76,
      "end": 77,
      "loc": {
        "start": {
          "line": 2,
          "column": 49
        },
        "end": {
          "line": 2,
          "column": 50
        }
      }
    },
    {
      "type": {
        "label": "name",
        "beforeExpr": false,
        "startsExpr": true,
        "rightAssociative": false,
        "isLoop": false,
        "isAssign": false,
        "prefix": false,
        "postfix": false,
        "binop": null
      },
      "value": "wrapperCol",
      "start": 80,
      "end": 90,
      "loc": {
        "start": {
          "line": 3,
          "column": 2
        },
        "end": {
          "line": 3,
          "column": 12
        }
      }
    },
    {
      "type": {
        "label": ":",
        "beforeExpr": true,
        "startsExpr": false,
        "rightAssociative": false,
        "isLoop": false,
        "isAssign": false,
        "prefix": false,
        "postfix": false,
        "binop": null,
        "updateContext": null
      },
      "start": 90,
      "end": 91,
      "loc": {
        "start": {
          "line": 3,
          "column": 12
        },
        "end": {
          "line": 3,
          "column": 13
        }
      }
    },
    {
      "type": {
        "label": "{",
        "beforeExpr": true,
        "startsExpr": true,
        "rightAssociative": false,
        "isLoop": false,
        "isAssign": false,
        "prefix": false,
        "postfix": false,
        "binop": null
      },
      "start": 92,
      "end": 93,
      "loc": {
        "start": {
          "line": 3,
          "column": 14
        },
        "end": {
          "line": 3,
          "column": 15
        }
      }
    },
    {
      "type": {
        "label": "name",
        "beforeExpr": false,
        "startsExpr": true,
        "rightAssociative": false,
        "isLoop": false,
        "isAssign": false,
        "prefix": false,
        "postfix": false,
        "binop": null
      },
      "value": "xs",
      "start": 94,
      "end": 96,
      "loc": {
        "start": {
          "line": 3,
          "column": 16
        },
        "end": {
          "line": 3,
          "column": 18
        }
      }
    },
    {
      "type": {
        "label": ":",
        "beforeExpr": true,
        "startsExpr": false,
        "rightAssociative": false,
        "isLoop": false,
        "isAssign": false,
        "prefix": false,
        "postfix": false,
        "binop": null,
        "updateContext": null
      },
      "start": 96,
      "end": 97,
      "loc": {
        "start": {
          "line": 3,
          "column": 18
        },
        "end": {
          "line": 3,
          "column": 19
        }
      }
    },
    {
      "type": {
        "label": "{",
        "beforeExpr": true,
        "startsExpr": true,
        "rightAssociative": false,
        "isLoop": false,
        "isAssign": false,
        "prefix": false,
        "postfix": false,
        "binop": null
      },
      "start": 98,
      "end": 99,
      "loc": {
        "start": {
          "line": 3,
          "column": 20
        },
        "end": {
          "line": 3,
          "column": 21
        }
      }
    },
    {
      "type": {
        "label": "name",
        "beforeExpr": false,
        "startsExpr": true,
        "rightAssociative": false,
        "isLoop": false,
        "isAssign": false,
        "prefix": false,
        "postfix": false,
        "binop": null
      },
      "value": "span",
      "start": 100,
      "end": 104,
      "loc": {
        "start": {
          "line": 3,
          "column": 22
        },
        "end": {
          "line": 3,
          "column": 26
        }
      }
    },
    {
      "type": {
        "label": ":",
        "beforeExpr": true,
        "startsExpr": false,
        "rightAssociative": false,
        "isLoop": false,
        "isAssign": false,
        "prefix": false,
        "postfix": false,
        "binop": null,
        "updateContext": null
      },
      "start": 104,
      "end": 105,
      "loc": {
        "start": {
          "line": 3,
          "column": 26
        },
        "end": {
          "line": 3,
          "column": 27
        }
      }
    },
    {
      "type": {
        "label": "num",
        "beforeExpr": false,
        "startsExpr": true,
        "rightAssociative": false,
        "isLoop": false,
        "isAssign": false,
        "prefix": false,
        "postfix": false,
        "binop": null,
        "updateContext": null
      },
      "value": 24,
      "start": 106,
      "end": 108,
      "loc": {
        "start": {
          "line": 3,
          "column": 28
        },
        "end": {
          "line": 3,
          "column": 30
        }
      }
    },
    {
      "type": {
        "label": "}",
        "beforeExpr": false,
        "startsExpr": false,
        "rightAssociative": false,
        "isLoop": false,
        "isAssign": false,
        "prefix": false,
        "postfix": false,
        "binop": null
      },
      "start": 109,
      "end": 110,
      "loc": {
        "start": {
          "line": 3,
          "column": 31
        },
        "end": {
          "line": 3,
          "column": 32
        }
      }
    },
    {
      "type": {
        "label": ",",
        "beforeExpr": true,
        "startsExpr": false,
        "rightAssociative": false,
        "isLoop": false,
        "isAssign": false,
        "prefix": false,
        "postfix": false,
        "binop": null,
        "updateContext": null
      },
      "start": 110,
      "end": 111,
      "loc": {
        "start": {
          "line": 3,
          "column": 32
        },
        "end": {
          "line": 3,
          "column": 33
        }
      }
    },
    {
      "type": {
        "label": "name",
        "beforeExpr": false,
        "startsExpr": true,
        "rightAssociative": false,
        "isLoop": false,
        "isAssign": false,
        "prefix": false,
        "postfix": false,
        "binop": null
      },
      "value": "sm",
      "start": 112,
      "end": 114,
      "loc": {
        "start": {
          "line": 3,
          "column": 34
        },
        "end": {
          "line": 3,
          "column": 36
        }
      }
    },
    {
      "type": {
        "label": ":",
        "beforeExpr": true,
        "startsExpr": false,
        "rightAssociative": false,
        "isLoop": false,
        "isAssign": false,
        "prefix": false,
        "postfix": false,
        "binop": null,
        "updateContext": null
      },
      "start": 114,
      "end": 115,
      "loc": {
        "start": {
          "line": 3,
          "column": 36
        },
        "end": {
          "line": 3,
          "column": 37
        }
      }
    },
    {
      "type": {
        "label": "{",
        "beforeExpr": true,
        "startsExpr": true,
        "rightAssociative": false,
        "isLoop": false,
        "isAssign": false,
        "prefix": false,
        "postfix": false,
        "binop": null
      },
      "start": 116,
      "end": 117,
      "loc": {
        "start": {
          "line": 3,
          "column": 38
        },
        "end": {
          "line": 3,
          "column": 39
        }
      }
    },
    {
      "type": {
        "label": "name",
        "beforeExpr": false,
        "startsExpr": true,
        "rightAssociative": false,
        "isLoop": false,
        "isAssign": false,
        "prefix": false,
        "postfix": false,
        "binop": null
      },
      "value": "span",
      "start": 118,
      "end": 122,
      "loc": {
        "start": {
          "line": 3,
          "column": 40
        },
        "end": {
          "line": 3,
          "column": 44
        }
      }
    },
    {
      "type": {
        "label": ":",
        "beforeExpr": true,
        "startsExpr": false,
        "rightAssociative": false,
        "isLoop": false,
        "isAssign": false,
        "prefix": false,
        "postfix": false,
        "binop": null,
        "updateContext": null
      },
      "start": 122,
      "end": 123,
      "loc": {
        "start": {
          "line": 3,
          "column": 44
        },
        "end": {
          "line": 3,
          "column": 45
        }
      }
    },
    {
      "type": {
        "label": "num",
        "beforeExpr": false,
        "startsExpr": true,
        "rightAssociative": false,
        "isLoop": false,
        "isAssign": false,
        "prefix": false,
        "postfix": false,
        "binop": null,
        "updateContext": null
      },
      "value": 12,
      "start": 124,
      "end": 126,
      "loc": {
        "start": {
          "line": 3,
          "column": 46
        },
        "end": {
          "line": 3,
          "column": 48
        }
      }
    },
    {
      "type": {
        "label": "}",
        "beforeExpr": false,
        "startsExpr": false,
        "rightAssociative": false,
        "isLoop": false,
        "isAssign": false,
        "prefix": false,
        "postfix": false,
        "binop": null
      },
      "start": 127,
      "end": 128,
      "loc": {
        "start": {
          "line": 3,
          "column": 49
        },
        "end": {
          "line": 3,
          "column": 50
        }
      }
    },
    {
      "type": {
        "label": "}",
        "beforeExpr": false,
        "startsExpr": false,
        "rightAssociative": false,
        "isLoop": false,
        "isAssign": false,
        "prefix": false,
        "postfix": false,
        "binop": null
      },
      "start": 129,
      "end": 130,
      "loc": {
        "start": {
          "line": 3,
          "column": 51
        },
        "end": {
          "line": 3,
          "column": 52
        }
      }
    },
    {
      "type": {
        "label": ",",
        "beforeExpr": true,
        "startsExpr": false,
        "rightAssociative": false,
        "isLoop": false,
        "isAssign": false,
        "prefix": false,
        "postfix": false,
        "binop": null,
        "updateContext": null
      },
      "start": 130,
      "end": 131,
      "loc": {
        "start": {
          "line": 3,
          "column": 52
        },
        "end": {
          "line": 3,
          "column": 53
        }
      }
    },
    {
      "type": {
        "label": "}",
        "beforeExpr": false,
        "startsExpr": false,
        "rightAssociative": false,
        "isLoop": false,
        "isAssign": false,
        "prefix": false,
        "postfix": false,
        "binop": null
      },
      "start": 132,
      "end": 133,
      "loc": {
        "start": {
          "line": 4,
          "column": 0
        },
        "end": {
          "line": 4,
          "column": 1
        }
      }
    },
    {
      "type": {
        "label": ";",
        "beforeExpr": true,
        "startsExpr": false,
        "rightAssociative": false,
        "isLoop": false,
        "isAssign": false,
        "prefix": false,
        "postfix": false,
        "binop": null,
        "updateContext": null
      },
      "start": 133,
      "end": 134,
      "loc": {
        "start": {
          "line": 4,
          "column": 1
        },
        "end": {
          "line": 4,
          "column": 2
        }
      }
    },
    {
      "type": {
        "label": "name",
        "beforeExpr": false,
        "startsExpr": true,
        "rightAssociative": false,
        "isLoop": false,
        "isAssign": false,
        "prefix": false,
        "postfix": false,
        "binop": null
      },
      "value": "exports",
      "start": 136,
      "end": 143,
      "loc": {
        "start": {
          "line": 6,
          "column": 0
        },
        "end": {
          "line": 6,
          "column": 7
        }
      }
    },
    {
      "type": {
        "label": ".",
        "beforeExpr": false,
        "startsExpr": false,
        "rightAssociative": false,
        "isLoop": false,
        "isAssign": false,
        "prefix": false,
        "postfix": false,
        "binop": null,
        "updateContext": null
      },
      "start": 143,
      "end": 144,
      "loc": {
        "start": {
          "line": 6,
          "column": 7
        },
        "end": {
          "line": 6,
          "column": 8
        }
      }
    },
    {
      "type": {
        "label": "name",
        "beforeExpr": false,
        "startsExpr": true,
        "rightAssociative": false,
        "isLoop": false,
        "isAssign": false,
        "prefix": false,
        "postfix": false,
        "binop": null
      },
      "value": "tailLayout",
      "start": 144,
      "end": 154,
      "loc": {
        "start": {
          "line": 6,
          "column": 8
        },
        "end": {
          "line": 6,
          "column": 18
        }
      }
    },
    {
      "type": {
        "label": "=",
        "beforeExpr": true,
        "startsExpr": false,
        "rightAssociative": false,
        "isLoop": false,
        "isAssign": true,
        "prefix": false,
        "postfix": false,
        "binop": null,
        "updateContext": null
      },
      "value": "=",
      "start": 155,
      "end": 156,
      "loc": {
        "start": {
          "line": 6,
          "column": 19
        },
        "end": {
          "line": 6,
          "column": 20
        }
      }
    },
    {
      "type": {
        "label": "{",
        "beforeExpr": true,
        "startsExpr": true,
        "rightAssociative": false,
        "isLoop": false,
        "isAssign": false,
        "prefix": false,
        "postfix": false,
        "binop": null
      },
      "start": 157,
      "end": 158,
      "loc": {
        "start": {
          "line": 6,
          "column": 21
        },
        "end": {
          "line": 6,
          "column": 22
        }
      }
    },
    {
      "type": {
        "label": "name",
        "beforeExpr": false,
        "startsExpr": true,
        "rightAssociative": false,
        "isLoop": false,
        "isAssign": false,
        "prefix": false,
        "postfix": false,
        "binop": null
      },
      "value": "wrapperCol",
      "start": 161,
      "end": 171,
      "loc": {
        "start": {
          "line": 7,
          "column": 2
        },
        "end": {
          "line": 7,
          "column": 12
        }
      }
    },
    {
      "type": {
        "label": ":",
        "beforeExpr": true,
        "startsExpr": false,
        "rightAssociative": false,
        "isLoop": false,
        "isAssign": false,
        "prefix": false,
        "postfix": false,
        "binop": null,
        "updateContext": null
      },
      "start": 171,
      "end": 172,
      "loc": {
        "start": {
          "line": 7,
          "column": 12
        },
        "end": {
          "line": 7,
          "column": 13
        }
      }
    },
    {
      "type": {
        "label": "{",
        "beforeExpr": true,
        "startsExpr": true,
        "rightAssociative": false,
        "isLoop": false,
        "isAssign": false,
        "prefix": false,
        "postfix": false,
        "binop": null
      },
      "start": 173,
      "end": 174,
      "loc": {
        "start": {
          "line": 7,
          "column": 14
        },
        "end": {
          "line": 7,
          "column": 15
        }
      }
    },
    {
      "type": {
        "label": "name",
        "beforeExpr": false,
        "startsExpr": true,
        "rightAssociative": false,
        "isLoop": false,
        "isAssign": false,
        "prefix": false,
        "postfix": false,
        "binop": null
      },
      "value": "offset",
      "start": 175,
      "end": 181,
      "loc": {
        "start": {
          "line": 7,
          "column": 16
        },
        "end": {
          "line": 7,
          "column": 22
        }
      }
    },
    {
      "type": {
        "label": ":",
        "beforeExpr": true,
        "startsExpr": false,
        "rightAssociative": false,
        "isLoop": false,
        "isAssign": false,
        "prefix": false,
        "postfix": false,
        "binop": null,
        "updateContext": null
      },
      "start": 181,
      "end": 182,
      "loc": {
        "start": {
          "line": 7,
          "column": 22
        },
        "end": {
          "line": 7,
          "column": 23
        }
      }
    },
    {
      "type": {
        "label": "num",
        "beforeExpr": false,
        "startsExpr": true,
        "rightAssociative": false,
        "isLoop": false,
        "isAssign": false,
        "prefix": false,
        "postfix": false,
        "binop": null,
        "updateContext": null
      },
      "value": 8,
      "start": 183,
      "end": 184,
      "loc": {
        "start": {
          "line": 7,
          "column": 24
        },
        "end": {
          "line": 7,
          "column": 25
        }
      }
    },
    {
      "type": {
        "label": ",",
        "beforeExpr": true,
        "startsExpr": false,
        "rightAssociative": false,
        "isLoop": false,
        "isAssign": false,
        "prefix": false,
        "postfix": false,
        "binop": null,
        "updateContext": null
      },
      "start": 184,
      "end": 185,
      "loc": {
        "start": {
          "line": 7,
          "column": 25
        },
        "end": {
          "line": 7,
          "column": 26
        }
      }
    },
    {
      "type": {
        "label": "name",
        "beforeExpr": false,
        "startsExpr": true,
        "rightAssociative": false,
        "isLoop": false,
        "isAssign": false,
        "prefix": false,
        "postfix": false,
        "binop": null
      },
      "value": "span",
      "start": 186,
      "end": 190,
      "loc": {
        "start": {
          "line": 7,
          "column": 27
        },
        "end": {
          "line": 7,
          "column": 31
        }
      }
    },
    {
      "type": {
        "label": ":",
        "beforeExpr": true,
        "startsExpr": false,
        "rightAssociative": false,
        "isLoop": false,
        "isAssign": false,
        "prefix": false,
        "postfix": false,
        "binop": null,
        "updateContext": null
      },
      "start": 190,
      "end": 191,
      "loc": {
        "start": {
          "line": 7,
          "column": 31
        },
        "end": {
          "line": 7,
          "column": 32
        }
      }
    },
    {
      "type": {
        "label": "num",
        "beforeExpr": false,
        "startsExpr": true,
        "rightAssociative": false,
        "isLoop": false,
        "isAssign": false,
        "prefix": false,
        "postfix": false,
        "binop": null,
        "updateContext": null
      },
      "value": 16,
      "start": 192,
      "end": 194,
      "loc": {
        "start": {
          "line": 7,
          "column": 33
        },
        "end": {
          "line": 7,
          "column": 35
        }
      }
    },
    {
      "type": {
        "label": "}",
        "beforeExpr": false,
        "startsExpr": false,
        "rightAssociative": false,
        "isLoop": false,
        "isAssign": false,
        "prefix": false,
        "postfix": false,
        "binop": null
      },
      "start": 195,
      "end": 196,
      "loc": {
        "start": {
          "line": 7,
          "column": 36
        },
        "end": {
          "line": 7,
          "column": 37
        }
      }
    },
    {
      "type": {
        "label": ",",
        "beforeExpr": true,
        "startsExpr": false,
        "rightAssociative": false,
        "isLoop": false,
        "isAssign": false,
        "prefix": false,
        "postfix": false,
        "binop": null,
        "updateContext": null
      },
      "start": 196,
      "end": 197,
      "loc": {
        "start": {
          "line": 7,
          "column": 37
        },
        "end": {
          "line": 7,
          "column": 38
        }
      }
    },
    {
      "type": {
        "label": "}",
        "beforeExpr": false,
        "startsExpr": false,
        "rightAssociative": false,
        "isLoop": false,
        "isAssign": false,
        "prefix": false,
        "postfix": false,
        "binop": null
      },
      "start": 198,
      "end": 199,
      "loc": {
        "start": {
          "line": 8,
          "column": 0
        },
        "end": {
          "line": 8,
          "column": 1
        }
      }
    },
    {
      "type": {
        "label": ";",
        "beforeExpr": true,
        "startsExpr": false,
        "rightAssociative": false,
        "isLoop": false,
        "isAssign": false,
        "prefix": false,
        "postfix": false,
        "binop": null,
        "updateContext": null
      },
      "start": 199,
      "end": 200,
      "loc": {
        "start": {
          "line": 8,
          "column": 1
        },
        "end": {
          "line": 8,
          "column": 2
        }
      }
    },
    {
      "type": {
        "label": "name",
        "beforeExpr": false,
        "startsExpr": true,
        "rightAssociative": false,
        "isLoop": false,
        "isAssign": false,
        "prefix": false,
        "postfix": false,
        "binop": null
      },
      "value": "exports",
      "start": 202,
      "end": 209,
      "loc": {
        "start": {
          "line": 10,
          "column": 0
        },
        "end": {
          "line": 10,
          "column": 7
        }
      }
    },
    {
      "type": {
        "label": ".",
        "beforeExpr": false,
        "startsExpr": false,
        "rightAssociative": false,
        "isLoop": false,
        "isAssign": false,
        "prefix": false,
        "postfix": false,
        "binop": null,
        "updateContext": null
      },
      "start": 209,
      "end": 210,
      "loc": {
        "start": {
          "line": 10,
          "column": 7
        },
        "end": {
          "line": 10,
          "column": 8
        }
      }
    },
    {
      "type": {
        "label": "name",
        "beforeExpr": false,
        "startsExpr": true,
        "rightAssociative": false,
        "isLoop": false,
        "isAssign": false,
        "prefix": false,
        "postfix": false,
        "binop": null
      },
      "value": "cardLayout",
      "start": 210,
      "end": 220,
      "loc": {
        "start": {
          "line": 10,
          "column": 8
        },
        "end": {
          "line": 10,
          "column": 18
        }
      }
    },
    {
      "type": {
        "label": "=",
        "beforeExpr": true,
        "startsExpr": false,
        "rightAssociative": false,
        "isLoop": false,
        "isAssign": true,
        "prefix": false,
        "postfix": false,
        "binop": null,
        "updateContext": null
      },
      "value": "=",
      "start": 221,
      "end": 222,
      "loc": {
        "start": {
          "line": 10,
          "column": 19
        },
        "end": {
          "line": 10,
          "column": 20
        }
      }
    },
    {
      "type": {
        "label": "{",
        "beforeExpr": true,
        "startsExpr": true,
        "rightAssociative": false,
        "isLoop": false,
        "isAssign": false,
        "prefix": false,
        "postfix": false,
        "binop": null
      },
      "start": 223,
      "end": 224,
      "loc": {
        "start": {
          "line": 10,
          "column": 21
        },
        "end": {
          "line": 10,
          "column": 22
        }
      }
    },
    {
      "type": {
        "label": "name",
        "beforeExpr": false,
        "startsExpr": true,
        "rightAssociative": false,
        "isLoop": false,
        "isAssign": false,
        "prefix": false,
        "postfix": false,
        "binop": null
      },
      "value": "borderRadius",
      "start": 227,
      "end": 239,
      "loc": {
        "start": {
          "line": 11,
          "column": 2
        },
        "end": {
          "line": 11,
          "column": 14
        }
      }
    },
    {
      "type": {
        "label": ":",
        "beforeExpr": true,
        "startsExpr": false,
        "rightAssociative": false,
        "isLoop": false,
        "isAssign": false,
        "prefix": false,
        "postfix": false,
        "binop": null,
        "updateContext": null
      },
      "start": 239,
      "end": 240,
      "loc": {
        "start": {
          "line": 11,
          "column": 14
        },
        "end": {
          "line": 11,
          "column": 15
        }
      }
    },
    {
      "type": {
        "label": "num",
        "beforeExpr": false,
        "startsExpr": true,
        "rightAssociative": false,
        "isLoop": false,
        "isAssign": false,
        "prefix": false,
        "postfix": false,
        "binop": null,
        "updateContext": null
      },
      "value": 10,
      "start": 241,
      "end": 243,
      "loc": {
        "start": {
          "line": 11,
          "column": 16
        },
        "end": {
          "line": 11,
          "column": 18
        }
      }
    },
    {
      "type": {
        "label": ",",
        "beforeExpr": true,
        "startsExpr": false,
        "rightAssociative": false,
        "isLoop": false,
        "isAssign": false,
        "prefix": false,
        "postfix": false,
        "binop": null,
        "updateContext": null
      },
      "start": 243,
      "end": 244,
      "loc": {
        "start": {
          "line": 11,
          "column": 18
        },
        "end": {
          "line": 11,
          "column": 19
        }
      }
    },
    {
      "type": {
        "label": "name",
        "beforeExpr": false,
        "startsExpr": true,
        "rightAssociative": false,
        "isLoop": false,
        "isAssign": false,
        "prefix": false,
        "postfix": false,
        "binop": null
      },
      "value": "marginTop",
      "start": 247,
      "end": 256,
      "loc": {
        "start": {
          "line": 12,
          "column": 2
        },
        "end": {
          "line": 12,
          "column": 11
        }
      }
    },
    {
      "type": {
        "label": ":",
        "beforeExpr": true,
        "startsExpr": false,
        "rightAssociative": false,
        "isLoop": false,
        "isAssign": false,
        "prefix": false,
        "postfix": false,
        "binop": null,
        "updateContext": null
      },
      "start": 256,
      "end": 257,
      "loc": {
        "start": {
          "line": 12,
          "column": 11
        },
        "end": {
          "line": 12,
          "column": 12
        }
      }
    },
    {
      "type": {
        "label": "num",
        "beforeExpr": false,
        "startsExpr": true,
        "rightAssociative": false,
        "isLoop": false,
        "isAssign": false,
        "prefix": false,
        "postfix": false,
        "binop": null,
        "updateContext": null
      },
      "value": 10,
      "start": 258,
      "end": 260,
      "loc": {
        "start": {
          "line": 12,
          "column": 13
        },
        "end": {
          "line": 12,
          "column": 15
        }
      }
    },
    {
      "type": {
        "label": ",",
        "beforeExpr": true,
        "startsExpr": false,
        "rightAssociative": false,
        "isLoop": false,
        "isAssign": false,
        "prefix": false,
        "postfix": false,
        "binop": null,
        "updateContext": null
      },
      "start": 260,
      "end": 261,
      "loc": {
        "start": {
          "line": 12,
          "column": 15
        },
        "end": {
          "line": 12,
          "column": 16
        }
      }
    },
    {
      "type": {
        "label": "}",
        "beforeExpr": false,
        "startsExpr": false,
        "rightAssociative": false,
        "isLoop": false,
        "isAssign": false,
        "prefix": false,
        "postfix": false,
        "binop": null
      },
      "start": 262,
      "end": 263,
      "loc": {
        "start": {
          "line": 13,
          "column": 0
        },
        "end": {
          "line": 13,
          "column": 1
        }
      }
    },
    {
      "type": {
        "label": ";",
        "beforeExpr": true,
        "startsExpr": false,
        "rightAssociative": false,
        "isLoop": false,
        "isAssign": false,
        "prefix": false,
        "postfix": false,
        "binop": null,
        "updateContext": null
      },
      "start": 263,
      "end": 264,
      "loc": {
        "start": {
          "line": 13,
          "column": 1
        },
        "end": {
          "line": 13,
          "column": 2
        }
      }
    },
    {
      "type": {
        "label": "eof",
        "beforeExpr": false,
        "startsExpr": false,
        "rightAssociative": false,
        "isLoop": false,
        "isAssign": false,
        "prefix": false,
        "postfix": false,
        "binop": null,
        "updateContext": null
      },
      "start": 265,
      "end": 265,
      "loc": {
        "start": {
          "line": 14,
          "column": 0
        },
        "end": {
          "line": 14,
          "column": 0
        }
      }
    }
  ]
}